OracleDB.py
robotframework_oracledb-2.0.2.dist-info/LICENSE
robotframework_oracledb-2.0.2.dist-info/METADATA
robotframework_oracledb-2.0.2.dist-info/WHEEL
robotframework_oracledb-2.0.2.dist-info/top_level.txt
robotframework_oracledb-2.0.2.dist-info/RECORD
