Metadata-Version: 2.1
Name: robotframework-oracledb
Version: 2.0.2
Summary: Robot Framework library for working with Oracle Database.
Home-page: https://github.com/peterservice-rnd/robotframework-oracledb
Author: Nexign
Author-email: MF_AIST_all@nexign-systems.com
License: Apache License 2.0
Keywords: testing testautomation robotframework autotest oracle database
Platform: UNKNOWN
Classifier: Development Status :: 5 - Production/Stable
Classifier: Intended Audience :: Developers
Classifier: Topic :: Software Development :: Testing
Classifier: License :: OSI Approved :: Apache Software License
Classifier: Programming Language :: Python :: 3.5
Classifier: Programming Language :: Python :: 3.6
Classifier: Framework :: Robot Framework :: Library
Requires-Dist: cx-Oracle
Requires-Dist: robotframework
Requires-Dist: sqlparse
